answer_displayers/CheckboxesField.py
answer_displayers/ClientSideFileUploadField.py
answer_displayers/DatePartsField.py
answer_displayers/EmailAddressField.py
answer_displayers/FreeTextField.py
answer_displayers/MonthYearField.py
answer_displayers/MultiInputField.py
answer_displayers/NumberField.py
answer_displayers/RadiosField.py
answer_displayers/TelephoneNumberField.py
answer_displayers/TextField.py
answer_displayers/UkAddressField.py
answer_displayers/WebsiteField.py
answer_displayers/YesNoField.py
answer_displayers/__init__.py
answer_displayers/shared/answer_displayer.py
answer_displayers/shared/dictionaries.py
funding_service_design_digital_form_builder_tools-1.0.2.dist-info/METADATA
funding_service_design_digital_form_builder_tools-1.0.2.dist-info/WHEEL
funding_service_design_digital_form_builder_tools-1.0.2.dist-info/top_level.txt
funding_service_design_digital_form_builder_tools-1.0.2.dist-info/RECORD
