Metadata-Version: 2.1
Name: funding-service-design-digital-form-builder-tools
Version: 1.0.2
Summary: Python tools for our fork of the digital-form-builder
Author-email: DLUHC <FundingServiceDesignTeam@levellingup.gov.uk>
Project-URL: Bug Tracker, https://github.com/communitiesuk/digital-form-builder/issues
Project-URL: Homepage, https://github.com/communitiesuk/digital-form-builder/
Classifier: Programming Language :: Python :: 3
Classifier: License :: OSI Approved :: MIT License
Classifier: Operating System :: OS Independent
Requires-Python: >=3.10
